congas/Interface.py
congas/__init__.py
congas/model_selection.py
congas/utils.py
congas/building_blocks/NB_likelihood.py
congas/building_blocks/__init__.py
congas/building_blocks/export_switch.py
congas/building_blocks/gaussian_likelihood.py
congas/building_blocks/poisson_likelihood.py
congas/data/example1_clust_ids.csv
congas/data/example1_cnv.csv
congas/data/example1_cnv_mat.csv
congas/data/example1_data.csv
congas/models/LatentCategorical.py
congas/models/Model.py
congas/models/__init__.py
congas-0.0.75.dist-info/LICENSE
congas-0.0.75.dist-info/METADATA
congas-0.0.75.dist-info/WHEEL
congas-0.0.75.dist-info/top_level.txt
congas-0.0.75.dist-info/RECORD
