Metadata-Version: 2.1
Name: congas
Version: 0.0.75
Summary: Copy Number genotyping from single cell RNA sequencing
Home-page: https://github.com/Militeee/congas
Author: Salvatore Milite
Author-email: militesalvatore@gmail.com
License: GPL-3.0
Keywords: scRNA scDNA RNA CNV CNA Cancer Copy-number Bioinformatics
Platform: UNKNOWN
Classifier: Development Status :: 3 - Alpha
Classifier: License :: OSI Approved :: GNU General Public License v3 (GPLv3)
Classifier: Programming Language :: Python :: 3.7
Classifier: Topic :: Scientific/Engineering :: Bio-Informatics
Requires-Dist: matplotlib (>=3.1)
Requires-Dist: pandas (>=1.0)
Requires-Dist: pyro-ppl (>=1.5)
Requires-Dist: numpy (>=1.18)
Requires-Dist: scikit-learn
